HSMTools/__init__.py
HSMTools/data_preparation/__init__.py
HSMTools/data_preparation/cli.py
HSMTools/data_preparation/data_folder_scanner.py
HSMTools/data_preparation/image_analyzer.py
HSMTools/data_preparation/image_pre_processor.py
HSMTools/data_preparation/image_visualizer.py
HSMTools/data_preparation/result_processor.py
HSMTools/data_preparation/sample_repository.py
HSMTools/data_preparation/sqlite_data_loader.py
HSMTools/data_preparation/temperature_image_extractor.py
HSMTools/data_reader/__init__.py
HSMTools/data_reader/data_reader.py
HSMTools/data_reader/sample.py
HSMTools/data_reader/sample_repository.py
HSMTools-0.1.3.dist-info/METADATA
HSMTools-0.1.3.dist-info/WHEEL
HSMTools-0.1.3.dist-info/entry_points.txt
HSMTools-0.1.3.dist-info/top_level.txt
HSMTools-0.1.3.dist-info/RECORD
